{
  "project_info": {
    "project_number": "553688533492",
    "project_id": "instamart-66565e84",
    "storage_bucket": "instamart-66565e84.firebasestorage.app"
  },
  "client": [
    {
      "client_info": {
        "mobilesdk_app_id": "1:553688533492:android:f6d2ab676d982a735811a1",
        "android_client_info": {
          "package_name": "com.example.instamart",
          "certificate_hash": "2e768433fb71b8c0cf13dd2ce38b062a422438ef"
        }
      },
      "oauth_client": [
        {
          "client_id": "553688533492-c3i4vbf26kj690gj3mt0090bah38a5b2.apps.googleusercontent.com",
          "client_type": 3
        }
      ],
      "api_key": [
        {
          "current_key": "AIzaSyCaVCwES8YzS6m16tM5qi2W9_rDaKW2pm8"
        }
      ],
      "services": {
        "appinvite_service": {
          "other_platform_oauth_client": [
            {
              "client_id": "553688533492-c3i4vbf26kj690gj3mt0090bah38a5b2.apps.googleusercontent.com",
              "client_type": 3
            }
          ]
        }
      }
    }
  ],
  "configuration_version": "1"
}